rknpu-1.5.2.dist-info/METADATA
rknpu-1.5.2.dist-info/WHEEL
rknpu.libs/librknnrt-db603b2a.so
rknpu/__init__.py
rknpu/rknpu.cpython-38-aarch64-linux-gnu.so
rknpu-1.5.2.dist-info/RECORD
