Metadata-Version: 2.1
Name: rknpu
Version: 1.5.2
Summary: rknpu python bind with rust backend
Author: TsinghTech <vision@qingtong.cn>
Author-email: TsinghTech <vision@qingtong.cn>
License: Apache-2.0
Project-URL: Source Code, https://github.com/tsinghtech-research/rknpu
